pression_index_st/__init__.py
pression_index_st/heat_map_consistent_altair.py
pression_index_st/polar_bar_plotly.py
pression_index_st/transformations.py
pression_index_st-0.1.0.dist-info/LICENSE
pression_index_st-0.1.0.dist-info/WHEEL
pression_index_st-0.1.0.dist-info/METADATA
pression_index_st-0.1.0.dist-info/RECORD
