Metadata-Version: 2.1
Name: pression_index_st
Version: 0.1.0
Summary: A template Streamlit app
Home-page: https://github.com/niesfutbol/pression_index_streamlit
Author: NIES
Author-email: nepo@nies.futbol
Requires-Python: >=3.9
Classifier: License :: OSI Approved :: GNU General Public License v3 or later (GPLv3+)
